{
  "destination": [
    {
      "id": 1,
      "value": 70,
      "label": "Atlanta"
    },
    {
      "id": 2,
      "value": 149,
      "label": "Boston"
    },
    {
      "id": 3,
      "value": 5034,
      "label": "Boston"
    },
    {
      "id": 4,
      "value": 34501,
      "label": "Celebration"
    },
    {
      "id": 5,
      "value": 40418,
      "label": "Edgewood"
    },
    {
      "id": 6,
      "value": 39505,
      "label": "Gotha"
    },
    {
      "id": 7,
      "value": 21017,
      "label": "Haines City"
    },
    {
      "id": 8,
      "value": 10,
      "label": "Los Angeles"
    },
    {
      "id": 9,
      "value": 72,
      "label": "Miami"
    },
    {
      "id": 10,
      "value": 18421,
      "label": "Montverde"
    },
    {
      "id": 11,
      "value": 54,
      "label": "New York"
    },
    {
      "id": 12,
      "value": 23767,
      "label": "Ocoee"
    },
    {
      "id": 13,
      "value": 32190,
      "label": "Orlando area"
    },
    {
      "id": 14,
      "value": 11531,
      "label": "Poinciana"
    },
    {
      "id": 15,
      "value": 10772,
      "label": "Polk City"
    },
    {
      "id": 16,
      "value": 17969,
      "label": "San Francisco Bay"
    },
    {
      "id": 17,
      "value": 17365,
      "label": "St. Cloud"
    },
    {
      "id": 18,
      "value": 24263,
      "label": "Walt Disney World\u00ae Resort"
    },
    {
      "id": 19,
      "value": 277,
      "label": "Washington"
    },
    {
      "id": 20,
      "value": 49764,
      "label": "Windermere"
    },
    {
      "id": 21,
      "value": 22282,
      "label": "Winter Garden"
    }
  ],
  "hotels": [
    {
      "id": 5018105,
      "name": "Woogo Central Park - Tempo Apartments",
      "address": "240 West 73rd Street",
      "city": "New York",
      "state": null,
      "country_code": "US",
      "hotel_rating": 4,
      "phone_number": "18005740835",
      "website": null,
      "image": "https://images.unsplash.com/photo-1479502806991-251c94be6b15?q=80&w=2070&auto=format&fit=crop&ixlib=rb-4.1.0&ixid=M3wxMjA3fDB8MHxwaG90by1wYWdlfHx8fGVufDB8fHx8fA%3D%3D",
      "pricePerNight": 325,
      "childrenFriendly": true,
      "petsAllowed": true
    },
    {
      "id": 11003176,
      "name": "Amolite Hotel",
      "address": "Avenida Curitiba, 811",
      "city": "New York",
      "state": null,
      "country_code": "BR",
      "hotel_rating": 0,
      "phone_number": null,
      "website": null,
      "image": "https://images.unsplash.com/photo-1456410826655-1ade96049e79?q=80&w=1936&auto=format&fit=crop&ixlib=rb-4.1.0&ixid=M3wxMjA3fDB8MHxwaG90by1wYWdlfHx8fGVufDB8fHx8fA%3D%3D",
      "pricePerNight": 336,
      "childrenFriendly": true,
      "petsAllowed": false
    },
    {
      "id": 747134,
      "name": "Redford Hotel",
      "address": "136 Ludlow Street",
      "city": "New York",
      "state": "NY",
      "country_code": "US",
      "hotel_rating": 3.5,
      "phone_number": "212260414",
      "website": null,
      "image": "https://images.unsplash.com/photo-1683219390820-02c6fc5243ec?q=80&w=2070&auto=format&fit=crop&ixlib=rb-4.1.0&ixid=M3wxMjA3fDB8MHxwaG90by1wYWdlfHx8fGVufDB8fHx8fA%3D%3D",
      "pricePerNight": 268,
      "childrenFriendly": true,
      "petsAllowed": true
    },
    {
      "id": 720550,
      "name": "Hotel Richland New York",
      "address": "5 Allen Street",
      "city": "New York",
      "state": "NY",
      "country_code": "US",
      "hotel_rating": 3,
      "phone_number": "1 212 2191018",
      "website": null,
      "image": "https://plus.unsplash.com/premium_photo-1749200412744-df6cf06f0496?q=80&w=2065&auto=format&fit=crop&ixlib=rb-4.1.0&ixid=M3wxMjA3fDB8MHxwaG90by1wYWdlfHx8fGVufDB8fHx8fA%3D%3D",
      "pricePerNight": 268,
      "childrenFriendly": false,
      "petsAllowed": true
    },
    {
      "id": 797074,
      "name": "Studio Lux Times Square",
      "address": "between 9 Avenue and 8 Avenue",
      "city": "New York",
      "state": "NY",
      "country_code": "US",
      "hotel_rating": 2.5,
      "phone_number": null,
      "website": null,
      "image": "https://plus.unsplash.com/premium_photo-1683888229114-183b04b18e4d?q=80&w=2127&auto=format&fit=crop&ixlib=rb-4.1.0&ixid=M3wxMjA3fDB8MHxwaG90by1wYWdlfHx8fGVufDB8fHx8fA%3D%3D",
      "pricePerNight": 351,
      "childrenFriendly": false,
      "petsAllowed": false
    },
    {
      "id": 742987,
      "name": "The Bowery Hotel",
      "address": "335 Bowery",
      "city": "New York",
      "state": "NY",
      "country_code": "US",
      "hotel_rating": 4,
      "phone_number": null,
      "website": null,
      "image": "https://images.unsplash.com/photo-1675438946665-2226c1878a68?q=80&w=1974&auto=format&fit=crop&ixlib=rb-4.1.0&ixid=M3wxMjA3fDB8MHxwaG90by1wYWdlfHx8fGVufDB8fHx8fA%3D%3D",
      "pricePerNight": 391,
      "childrenFriendly": true,
      "petsAllowed": true
    },
    {
      "id": 743452,
      "name": "AC Hotel by Marriott New York Times Square",
      "address": "260 West 40th Street",
      "city": "New York",
      "state": "NY",
      "country_code": "US",
      "hotel_rating": 3.5,
      "phone_number": "1-212-398-2700",
      "website": null,
      "image": "https://images.unsplash.com/photo-1693080951268-a7cd68192683?w=600&auto=format&fit=crop&q=60&ixlib=rb-4.1.0&ixid=M3wxMjA3fDB8MHxzZWFyY2h8Njd8fGhvdGVsJTIwbmV3JTIweW9ya3xlbnwwfHwwfHx8MA%3D%3D",
      "pricePerNight": 352,
      "childrenFriendly": true,
      "petsAllowed": true
    },
    {
      "id": 260469,
      "name": "The Ridge Hotel",
      "address": "151 East Houston Street",
      "city": "New York",
      "state": "NY",
      "country_code": "US",
      "hotel_rating": 3,
      "phone_number": "1 212 777-0012",
      "website": null,
      "image": "https://images.unsplash.com/photo-1693323932877-04b1a3068ade?q=80&w=1965&auto=format&fit=crop&ixlib=rb-4.1.0&ixid=M3wxMjA3fDB8MHxwaG90by1wYWdlfHx8fGVufDB8fHx8fA%3D%3D",
      "pricePerNight": 136,
      "childrenFriendly": false,
      "petsAllowed": false
    },
    {
      "id": 740399,
      "name": "SoHo 54 Hotel",
      "address": "54 Watts St",
      "city": "New York",
      "state": "NY",
      "country_code": "US",
      "hotel_rating": 3,
      "phone_number": null,
      "website": null,
      "image": "https://images.unsplash.com/photo-1708272958186-e80ee0db4e49?w=600&auto=format&fit=crop&q=60&ixlib=rb-4.1.0&ixid=M3wxMjA3fDB8MHxzZWFyY2h8NTB8fGhvdGVsJTIwbmV3JTIweW9ya3xlbnwwfHwwfHx8MA%3D%3D",
      "pricePerNight": 291,
      "childrenFriendly": true,
      "petsAllowed": false
    },
    {
      "id": 5018104,
      "name": "Hotel Alexander",
      "address": "306 W 94th St",
      "city": "New York",
      "state": null,
      "country_code": "US",
      "hotel_rating": 3,
      "phone_number": "XX",
      "website": null,
      "image": "https://plus.unsplash.com/premium_photo-1725408137628-72756b761573?q=80&w=2070&auto=format&fit=crop&ixlib=rb-4.1.0&ixid=M3wxMjA3fDB8MHxwaG90by1wYWdlfHx8fGVufDB8fHx8fA%3D%3D",
      "pricePerNight": 369,
      "childrenFriendly": true,
      "petsAllowed": true
    },
    {
      "id": 792811,
      "name": "Parker New York, A Hyatt Affiliate Property",
      "address": "119 West 56th Street",
      "city": "New York",
      "state": "NY",
      "country_code": "US",
      "hotel_rating": 4.5,
      "phone_number": null,
      "website": null,
      "image": "https://images.unsplash.com/photo-1683219386001-738ce8d83f7e?q=80&w=1974&auto=format&fit=crop&ixlib=rb-4.1.0&ixid=M3wxMjA3fDB8MHxwaG90by1wYWdlfHx8fGVufDB8fHx8fA%3D%3D",
      "pricePerNight": 340,
      "childrenFriendly": false,
      "petsAllowed": true
    },
    {
      "id": 804220,
      "name": "Central Park View B&B",
      "address": "301 West 110th Street",
      "city": "New York",
      "state": "NY",
      "country_code": "US",
      "hotel_rating": 2.5,
      "phone_number": null,
      "website": null,
      "image": "https://plus.unsplash.com/premium_photo-1723901831083-b2dda0944e12?w=600&auto=format&fit=crop&q=60&ixlib=rb-4.1.0&ixid=M3wxMjA3fDB8MHxwaG90by1yZWxhdGVkfDF8fHxlbnwwfHx8fHw%3D",
      "pricePerNight": 356,
      "childrenFriendly": false,
      "petsAllowed": false
    },
    {
      "id": 5018107,
      "name": "Staten Island Hotel",
      "address": "1415 Richmond Ave",
      "city": "New York",
      "state": null,
      "country_code": "US",
      "hotel_rating": 3,
      "phone_number": "17186985000",
      "website": null,
      "image": "https://plus.unsplash.com/premium_photo-1694475315783-512c95173330?w=600&auto=format&fit=crop&q=60&ixlib=rb-4.1.0&ixid=M3wxMjA3fDB8MHxzZWFyY2h8MjF8fGhvdGVsJTIwbmV3JTIweW9ya3xlbnwwfHwwfHx8MA%3D%3D",
      "pricePerNight": 97,
      "childrenFriendly": true,
      "petsAllowed": true
    },
    {
      "id": 700390,
      "name": "Mondrian Park Avenue",
      "address": "444 Park Ave S",
      "city": "New York",
      "state": "NY",
      "country_code": "US",
      "hotel_rating": 4.5,
      "phone_number": null,
      "website": null,
      "image": "https://images.unsplash.com/photo-1592134873587-feab66402390?w=600&auto=format&fit=crop&q=60&ixlib=rb-4.1.0&ixid=M3wxMjA3fDB8MHxzZWFyY2h8MjZ8fGhvdGVsJTIwbmV3JTIweW9ya3xlbnwwfHwwfHx8MA%3D%3D",
      "pricePerNight": 383,
      "childrenFriendly": false,
      "petsAllowed": true
    },
    {
      "id": 742946,
      "name": "Pod Times Square",
      "address": "400 W 42nd Street",
      "city": "New York",
      "state": "NY",
      "country_code": "US",
      "hotel_rating": 3,
      "phone_number": null,
      "website": null,
      "image": "https://images.unsplash.com/photo-1590508992931-1ee8f953f2f6?w=600&auto=format&fit=crop&q=60&ixlib=rb-4.1.0&ixid=M3wxMjA3fDB8MHxzZWFyY2h8MjV8fGhvdGVsJTIwbmV3JTIweW9ya3xlbnwwfHwwfHx8MA%3D%3D",
      "pricePerNight": 207,
      "childrenFriendly": true,
      "petsAllowed": true
    },
    {
      "id": 776932,
      "name": "Freehand New York",
      "address": "23 Lexington Ave",
      "city": "New York",
      "state": "NY",
      "country_code": "US",
      "hotel_rating": 4,
      "phone_number": "121-247-51920",
      "website": "https://freehandhotels.com/new-york/rooms/",
      "image": "https://images.unsplash.com/photo-1675201459210-e64fee1e4e3e?w=600&auto=format&fit=crop&q=60&ixlib=rb-4.1.0&ixid=M3wxMjA3fDB8MHxzZWFyY2h8Mjh8fGhvdGVsJTIwbmV3JTIweW9ya3xlbnwwfHwwfHx8MA%3D%3D",
      "pricePerNight": 53,
      "childrenFriendly": true,
      "petsAllowed": false
    },
    {
      "id": 741741,
      "name": "The Grand NYC",
      "address": "38 West 31st Street",
      "city": "New York",
      "state": "NY",
      "country_code": "US",
      "hotel_rating": 2,
      "phone_number": null,
      "website": null,
      "image": "https://plus.unsplash.com/premium_photo-1694475027390-8fd837fb67e8?w=600&auto=format&fit=crop&q=60&ixlib=rb-4.1.0&ixid=M3wxMjA3fDB8MHxzZWFyY2h8MzF8fGhvdGVsJTIwbmV3JTIweW9ya3xlbnwwfHwwfHx8MA%3D%3D",
      "pricePerNight": 157,
      "childrenFriendly": true,
      "petsAllowed": false
    },
    {
      "id": 716815,
      "name": "Hello Broadway",
      "address": "38 west 31 st",
      "city": "New York",
      "state": "NY",
      "country_code": "US",
      "hotel_rating": 3,
      "phone_number": null,
      "website": null,
      "image": "https://images.unsplash.com/photo-1702264388930-408041b12e1f?q=80&w=1974&auto=format&fit=crop&ixlib=rb-4.1.0&ixid=M3wxMjA3fDB8MHxwaG90by1wYWdlfHx8fGVufDB8fHx8fA%3D%3D",
      "pricePerNight": 297,
      "childrenFriendly": true,
      "petsAllowed": true
    },
    {
      "id": 802583,
      "name": "The Dominick",
      "address": "246 Spring Street",
      "city": "New York",
      "state": "NY",
      "country_code": "US",
      "hotel_rating": 5,
      "phone_number": "+1 212 842 5500",
      "website": null,
      "image": "https://images.unsplash.com/photo-1561198928-d649f64aefd1?w=600&auto=format&fit=crop&q=60&ixlib=rb-4.1.0&ixid=M3wxMjA3fDB8MHxzZWFyY2h8Mzh8fGhvdGVsJTIwbmV3JTIweW9ya3xlbnwwfHwwfHx8MA%3D%3D",
      "pricePerNight": 150,
      "childrenFriendly": true,
      "petsAllowed": false
    },
    {
      "id": 5018106,
      "name": "HomeStay NYC",
      "address": "49 Catherine Street",
      "city": "New York",
      "state": null,
      "country_code": "US",
      "hotel_rating": 3,
      "phone_number": null,
      "website": null,
      "image": "https://images.unsplash.com/photo-1660166376836-dc0e11ce4d47?w=600&auto=format&fit=crop&q=60&ixlib=rb-4.1.0&ixid=M3wxMjA3fDB8MHxzZWFyY2h8NDF8fGhvdGVsJTIwbmV3JTIweW9ya3xlbnwwfHwwfHx8MA%3D%3D",
      "pricePerNight": 315,
      "childrenFriendly": false,
      "petsAllowed": false
    },
    {
      "id": 751736,
      "name": "Fairfield Inn & Suites by Marriott/World Trade Center Area",
      "address": "100 Greenwich St",
      "city": "New York",
      "state": "NY",
      "country_code": "US",
      "hotel_rating": 3,
      "phone_number": "703-261-5677",
      "website": null,
      "image": "https://images.unsplash.com/photo-1653859798701-455ef9f1f0a9?q=80&w=2070&auto=format&fit=crop&ixlib=rb-4.1.0&ixid=M3wxMjA3fDB8MHxwaG90by1wYWdlfHx8fGVufDB8fHx8fA%3D%3D",
      "pricePerNight": 323,
      "childrenFriendly": true,
      "petsAllowed": true
    },
    {
      "id": 386689,
      "name": "Back Bay Suites",
      "address": "11 Hereford St.",
      "city": "Boston",
      "state": "MA",
      "country_code": "US",
      "hotel_rating": 2.5,
      "phone_number": null,
      "website": null,
      "pricePerNight": 233,
      "childrenFriendly": false,
      "petsAllowed": true,
      "image": "https://source.unsplash.com/featured/?hotel,room,9443"
    },
    {
      "id": 567484,
      "name": "Global Luxury Suites at The Theatre District",
      "address": "99 Kneeland St.",
      "city": "Boston",
      "state": "MA",
      "country_code": "US",
      "hotel_rating": 3.5,
      "phone_number": null,
      "website": null,
      "pricePerNight": 245,
      "childrenFriendly": false,
      "petsAllowed": false,
      "image": "https://source.unsplash.com/featured/?hotel,room,7695"
    },
    {
      "id": 677300,
      "name": "Vibrant 1BR in Fenway by Sonder",
      "address": "Beacon Street and Park dr",
      "city": "Boston",
      "state": "MA",
      "country_code": "US",
      "hotel_rating": 4,
      "phone_number": null,
      "website": null,
      "pricePerNight": 104,
      "childrenFriendly": false,
      "petsAllowed": false,
      "image": "https://source.unsplash.com/featured/?hotel,room,6393"
    },
    {
      "id": 820605,
      "name": "Unique 1BR in Financial District by Sonder",
      "address": "120 Milk St, Unit 801",
      "city": "Boston",
      "state": "MA",
      "country_code": "US",
      "hotel_rating": null,
      "phone_number": null,
      "website": null,
      "pricePerNight": 147,
      "childrenFriendly": true,
      "petsAllowed": false,
      "image": "https://source.unsplash.com/featured/?hotel,room,7603"
    },
    {
      "id": 731189,
      "name": "Charming 2BR in South End by Sonder",
      "address": "Columbia Road & G Street",
      "city": "Boston",
      "state": "MA",
      "country_code": "US",
      "hotel_rating": 3.5,
      "phone_number": null,
      "website": null,
      "pricePerNight": 54,
      "childrenFriendly": true,
      "petsAllowed": false,
      "image": "https://source.unsplash.com/featured/?hotel,room,7620"
    },
    {
      "id": 721848,
      "name": "Stunning 4BR in Downtown Crossing by Sonder",
      "address": "Hamilton Place",
      "city": "Boston",
      "state": "MA",
      "country_code": "US",
      "hotel_rating": 3.5,
      "phone_number": null,
      "website": null,
      "pricePerNight": 119,
      "childrenFriendly": true,
      "petsAllowed": false,
      "image": "https://source.unsplash.com/featured/?hotel,room,2675"
    },
    {
      "id": 677341,
      "name": "Classic 3BR in Allston by Sonder",
      "address": "Brainerd Road and Harvard St",
      "city": "Boston",
      "state": "MA",
      "country_code": "US",
      "hotel_rating": 3.5,
      "phone_number": null,
      "website": null,
      "pricePerNight": 249,
      "childrenFriendly": true,
      "petsAllowed": false,
      "image": "https://source.unsplash.com/featured/?hotel,room,3588"
    },
    {
      "id": 677347,
      "name": "Posh 2BR in Allston by Sonder",
      "address": "Western Avenue and N Harvard",
      "city": "Boston",
      "state": "MA",
      "country_code": "US",
      "hotel_rating": 3.5,
      "phone_number": null,
      "website": null,
      "pricePerNight": 82,
      "childrenFriendly": false,
      "petsAllowed": false,
      "image": "https://source.unsplash.com/featured/?hotel,room,172"
    },
    {
      "id": 810445,
      "name": "Sophisticated 2BR in Downtown Crossing by Sonder",
      "address": "Boylston Street",
      "city": "Boston",
      "state": "MA",
      "country_code": "US",
      "hotel_rating": 3.5,
      "phone_number": null,
      "website": null,
      "pricePerNight": 69,
      "childrenFriendly": false,
      "petsAllowed": true,
      "image": "https://source.unsplash.com/featured/?hotel,room,2633"
    },
    {
      "id": 677372,
      "name": "Posh Studio in Downtown Crossing by Sonder",
      "address": "Arch Street and Summer st",
      "city": "Boston",
      "state": "MA",
      "country_code": "US",
      "hotel_rating": 3,
      "phone_number": null,
      "website": null,
      "pricePerNight": 317,
      "childrenFriendly": true,
      "petsAllowed": false,
      "image": "https://source.unsplash.com/featured/?hotel,room,8919"
    },
    {
      "id": 822534,
      "name": "Playful 1BR in Fenway by Sonder",
      "address": "Commonwealth Avenue",
      "city": "Boston",
      "state": "MA",
      "country_code": "US",
      "hotel_rating": null,
      "phone_number": null,
      "website": null,
      "pricePerNight": 369,
      "childrenFriendly": true,
      "petsAllowed": true,
      "image": "https://source.unsplash.com/featured/?hotel,room,4353"
    },
    {
      "id": 793847,
      "name": "Stunning 1 BR In Allston by Sonder",
      "address": "75 Braintree St",
      "city": "Boston",
      "state": "MA",
      "country_code": "US",
      "hotel_rating": 4,
      "phone_number": null,
      "website": null,
      "pricePerNight": 94,
      "childrenFriendly": false,
      "petsAllowed": false,
      "image": "https://source.unsplash.com/featured/?hotel,room,2428"
    },
    {
      "id": 677396,
      "name": "Sonder - St. Mary's",
      "address": "Beacon Street and Park dr",
      "city": "Boston",
      "state": "MA",
      "country_code": "US",
      "hotel_rating": 4,
      "phone_number": null,
      "website": null,
      "pricePerNight": 149,
      "childrenFriendly": false,
      "petsAllowed": false,
      "image": "https://source.unsplash.com/featured/?hotel,room,7054"
    },
    {
      "id": 677411,
      "name": "Bright 2BR in Downtown Crossing by Sonder",
      "address": "Milk Street and Batterymarch st",
      "city": "Boston",
      "state": "MA",
      "country_code": "US",
      "hotel_rating": 3.5,
      "phone_number": null,
      "website": null,
      "pricePerNight": 66,
      "childrenFriendly": true,
      "petsAllowed": false,
      "image": "https://source.unsplash.com/featured/?hotel,room,1331"
    },
    {
      "id": 677410,
      "name": "Simple 1BR in Theater District by Sonder",
      "address": "Warrenton Street and Stuart St",
      "city": "Boston",
      "state": "MA",
      "country_code": "US",
      "hotel_rating": 3.5,
      "phone_number": null,
      "website": null,
      "pricePerNight": 95,
      "childrenFriendly": false,
      "petsAllowed": true,
      "image": "https://source.unsplash.com/featured/?hotel,room,4519"
    },
    {
      "id": 677425,
      "name": "Central 2BR in South End by Sonder",
      "address": "Tremont Street and Milford Street",
      "city": "Boston",
      "state": "MA",
      "country_code": "US",
      "hotel_rating": 4,
      "phone_number": null,
      "website": null,
      "pricePerNight": 275,
      "childrenFriendly": true,
      "petsAllowed": true,
      "image": "https://source.unsplash.com/featured/?hotel,room,5448"
    },
    {
      "id": 677426,
      "name": "Classic 1BR in Fenway by Sonder",
      "address": "Beacon Street and Park dr",
      "city": "Boston",
      "state": "MA",
      "country_code": "US",
      "hotel_rating": 4,
      "phone_number": null,
      "website": null,
      "pricePerNight": 242,
      "childrenFriendly": false,
      "petsAllowed": true,
      "image": "https://source.unsplash.com/featured/?hotel,room,7573"
    },
    {
      "id": 721859,
      "name": "Hip 3BR in Downtown Crossing by Sonder",
      "address": "Hamilton Place",
      "city": "Boston",
      "state": "MA",
      "country_code": "US",
      "hotel_rating": 4,
      "phone_number": null,
      "website": null,
      "pricePerNight": 89,
      "childrenFriendly": false,
      "petsAllowed": true,
      "image": "https://source.unsplash.com/featured/?hotel,room,7829"
    },
    {
      "id": 801610,
      "name": "Playful 2BR in South End by Sonder",
      "address": "Albany Street",
      "city": "Boston",
      "state": "MA",
      "country_code": "US",
      "hotel_rating": 4,
      "phone_number": null,
      "website": null,
      "pricePerNight": 51,
      "childrenFriendly": true,
      "petsAllowed": true,
      "image": "https://source.unsplash.com/featured/?hotel,room,5153"
    },
    {
      "id": 677429,
      "name": "Airy 2BR in Allston by Sonder",
      "address": "Western Avenue and N Harvard",
      "city": "Boston",
      "state": "MA",
      "country_code": "US",
      "hotel_rating": 3.5,
      "phone_number": null,
      "website": null,
      "pricePerNight": 269,
      "childrenFriendly": false,
      "petsAllowed": true,
      "image": "https://source.unsplash.com/featured/?hotel,room,335"
    },
    {
      "id": 677433,
      "name": "Bright 1BR in South End by Sonder",
      "address": "Harrison Avenue and Herald Street",
      "city": "Boston",
      "state": "MA",
      "country_code": "US",
      "hotel_rating": 4,
      "phone_number": null,
      "website": null,
      "pricePerNight": 226,
      "childrenFriendly": true,
      "petsAllowed": false,
      "image": "https://source.unsplash.com/featured/?hotel,room,2173"
    },
    {
      "id": 677449,
      "name": "Industrial 3BR in Downtown by Sonder",
      "address": "Washington Street and Essex St",
      "city": "Boston",
      "state": "MA",
      "country_code": "US",
      "hotel_rating": 4,
      "phone_number": null,
      "website": null,
      "pricePerNight": 119,
      "childrenFriendly": true,
      "petsAllowed": false,
      "image": "https://source.unsplash.com/featured/?hotel,room,6768"
    },
    {
      "id": 677450,
      "name": "Chic 1BR in Downtown Crossing by Sonder",
      "address": "Arch Street and Summer st",
      "city": "Boston",
      "state": "MA",
      "country_code": "US",
      "hotel_rating": 3.5,
      "phone_number": null,
      "website": null,
      "pricePerNight": 354,
      "childrenFriendly": false,
      "petsAllowed": true,
      "image": "https://source.unsplash.com/featured/?hotel,room,6139"
    },
    {
      "id": 677452,
      "name": "Sonder - Financial District",
      "address": "Milk Street and Batterymarch st",
      "city": "Boston",
      "state": "MA",
      "country_code": "US",
      "hotel_rating": 4,
      "phone_number": null,
      "website": null,
      "pricePerNight": 250,
      "childrenFriendly": false,
      "petsAllowed": false,
      "image": "https://source.unsplash.com/featured/?hotel,room,2519"
    },
    {
      "id": 677455,
      "name": "Bright Studio in Downtown Crossing by Sonder",
      "address": "Arch Street and Summer st",
      "city": "Boston",
      "state": "MA",
      "country_code": "US",
      "hotel_rating": 3,
      "phone_number": null,
      "website": null,
      "pricePerNight": 119,
      "childrenFriendly": true,
      "petsAllowed": true,
      "image": "https://source.unsplash.com/featured/?hotel,room,3257"
    },
    {
      "id": 677470,
      "name": "Central 3BR in South End by Sonder",
      "address": "Massachusetts Avenue and Washington st",
      "city": "Boston",
      "state": "MA",
      "country_code": "US",
      "hotel_rating": 4,
      "phone_number": null,
      "website": null,
      "pricePerNight": 115,
      "childrenFriendly": false,
      "petsAllowed": false,
      "image": "https://source.unsplash.com/featured/?hotel,room,6159"
    },
    {
      "id": 677476,
      "name": "Smart 2BR in Brighton by Sonder",
      "address": "Commonwealth Avenue and Chestnut Hill av",
      "city": "Boston",
      "state": "MA",
      "country_code": "US",
      "hotel_rating": 3.5,
      "phone_number": null,
      "website": null,
      "pricePerNight": 200,
      "childrenFriendly": false,
      "petsAllowed": false,
      "image": "https://source.unsplash.com/featured/?hotel,room,6350"
    },
    {
      "id": 677477,
      "name": "Hip 1BR in Allston by Sonder",
      "address": "Brainerd Road and Harvard St",
      "city": "Boston",
      "state": "MA",
      "country_code": "US",
      "hotel_rating": 3.5,
      "phone_number": null,
      "website": null,
      "pricePerNight": 190,
      "childrenFriendly": true,
      "petsAllowed": false,
      "image": "https://source.unsplash.com/featured/?hotel,room,8024"
    },
    {
      "id": 677480,
      "name": "Smart 1BR in Downtown Crossing by Sonder",
      "address": "Arch Street and Summer st",
      "city": "Boston",
      "state": "MA",
      "country_code": "US",
      "hotel_rating": 3.5,
      "phone_number": null,
      "website": null,
      "pricePerNight": 253,
      "childrenFriendly": true,
      "petsAllowed": true,
      "image": "https://source.unsplash.com/featured/?hotel,room,9063"
    },
    {
      "id": 677481,
      "name": "Hip 2BR in Allston by Sonder",
      "address": "Brainerd Road and Harvard St",
      "city": "Boston",
      "state": "MA",
      "country_code": "US",
      "hotel_rating": 3.5,
      "phone_number": null,
      "website": null,
      "pricePerNight": 218,
      "childrenFriendly": true,
      "petsAllowed": true,
      "image": "https://source.unsplash.com/featured/?hotel,room,3566"
    },
    {
      "id": 677519,
      "name": "Charming 1BR in Fenway by Sonder",
      "address": "Beacon Street and Park dr",
      "city": "Boston",
      "state": "MA",
      "country_code": "US",
      "hotel_rating": 4,
      "phone_number": null,
      "website": null,
      "pricePerNight": 296,
      "childrenFriendly": false,
      "petsAllowed": true,
      "image": "https://source.unsplash.com/featured/?hotel,room,5110"
    },
    {
      "id": 677520,
      "name": "Lively 1BR in Theater District by Sonder",
      "address": "Warrenton Street and Stuart St",
      "city": "Boston",
      "state": "MA",
      "country_code": "US",
      "hotel_rating": 3.5,
      "phone_number": null,
      "website": null,
      "pricePerNight": 292,
      "childrenFriendly": false,
      "petsAllowed": false,
      "image": "https://source.unsplash.com/featured/?hotel,room,7325"
    },
    {
      "id": 705227,
      "name": "Charming 1BR in Seaport by Sonder",
      "address": "D Street",
      "city": "Boston",
      "state": "MA",
      "country_code": "US",
      "hotel_rating": 3.5,
      "phone_number": null,
      "website": null,
      "pricePerNight": 274,
      "childrenFriendly": true,
      "petsAllowed": false,
      "image": "https://source.unsplash.com/featured/?hotel,room,7832"
    },
    {
      "id": 696618,
      "name": "Central 1BR in Fenway by Sonder",
      "address": "Brookline Avenue",
      "city": "Boston",
      "state": "MA",
      "country_code": "US",
      "hotel_rating": 4,
      "phone_number": null,
      "website": null,
      "pricePerNight": 50,
      "childrenFriendly": true,
      "petsAllowed": true,
      "image": "https://source.unsplash.com/featured/?hotel,room,1321"
    },
    {
      "id": 677526,
      "name": "Simple Studio in Downtown Crossing by Sonder",
      "address": "Arch Street and Summer st",
      "city": "Boston",
      "state": "MA",
      "country_code": "US",
      "hotel_rating": 3.5,
      "phone_number": null,
      "website": null,
      "pricePerNight": 78,
      "childrenFriendly": true,
      "petsAllowed": true,
      "image": "https://source.unsplash.com/featured/?hotel,room,370"
    },
    {
      "id": 677527,
      "name": "Modern 3BR in Brighton by Sonder",
      "address": "Larose Place and Monastery rd",
      "city": "Boston",
      "state": "MA",
      "country_code": "US",
      "hotel_rating": 3.5,
      "phone_number": null,
      "website": null,
      "pricePerNight": 291,
      "childrenFriendly": true,
      "petsAllowed": true,
      "image": "https://source.unsplash.com/featured/?hotel,room,6753"
    },
    {
      "id": 677528,
      "name": "Pleasant Back Bay Suites by Sonder",
      "address": "Newbury Street and Fairfield Street",
      "city": "Boston",
      "state": "MA",
      "country_code": "US",
      "hotel_rating": 3.5,
      "phone_number": null,
      "website": null,
      "pricePerNight": 202,
      "childrenFriendly": false,
      "petsAllowed": true,
      "image": "https://source.unsplash.com/featured/?hotel,room,5848"
    },
    {
      "id": 677537,
      "name": "Sonder - The Continuum",
      "address": "Western Avenue and N Harvard",
      "city": "Boston",
      "state": "MA",
      "country_code": "US",
      "hotel_rating": 3.5,
      "phone_number": null,
      "website": null,
      "pricePerNight": 390,
      "childrenFriendly": false,
      "petsAllowed": true,
      "image": "https://source.unsplash.com/featured/?hotel,room,6192"
    },
    {
      "id": 696614,
      "name": "Smart 1BR in Seaport by Sonder",
      "address": "D Street",
      "city": "Boston",
      "state": "MA",
      "country_code": "US",
      "hotel_rating": 3.5,
      "phone_number": null,
      "website": null,
      "pricePerNight": 383,
      "childrenFriendly": false,
      "petsAllowed": false,
      "image": "https://source.unsplash.com/featured/?hotel,room,8419"
    },
    {
      "id": 677694,
      "name": "Unique 2BR in Downtown Crossing by Sonder",
      "address": "Washington Street and Essex St",
      "city": "Boston",
      "state": "MA",
      "country_code": "US",
      "hotel_rating": 4,
      "phone_number": null,
      "website": null,
      "pricePerNight": 55,
      "childrenFriendly": false,
      "petsAllowed": false,
      "image": "https://source.unsplash.com/featured/?hotel,room,2397"
    },
    {
      "id": 677550,
      "name": "Posh Studio in Back Bay by Sonder",
      "address": "Newbury Street and Fairfield Street",
      "city": "Boston",
      "state": "MA",
      "country_code": "US",
      "hotel_rating": 3,
      "phone_number": null,
      "website": null,
      "pricePerNight": 301,
      "childrenFriendly": false,
      "petsAllowed": true,
      "image": "https://source.unsplash.com/featured/?hotel,room,2056"
    },
    {
      "id": 787996,
      "name": "Vibrant 2BR in Downtown Crossing by Sonder",
      "address": "Washington Street",
      "city": "Boston",
      "state": "MA",
      "country_code": "US",
      "hotel_rating": 4,
      "phone_number": null,
      "website": null,
      "pricePerNight": 108,
      "childrenFriendly": true,
      "petsAllowed": true,
      "image": "https://source.unsplash.com/featured/?hotel,room,3723"
    },
    {
      "id": 731262,
      "name": "Stunning 3BR in Downtown Crossing by Sonder",
      "address": "Hamilton Place & Tremont St.",
      "city": "Boston",
      "state": "MA",
      "country_code": "US",
      "hotel_rating": 3.5,
      "phone_number": null,
      "website": null,
      "pricePerNight": 309,
      "childrenFriendly": true,
      "petsAllowed": false,
      "image": "https://source.unsplash.com/featured/?hotel,room,6081"
    },
    {
      "id": 677559,
      "name": "Industrial 1BR in Downtown Crossing by Sonder",
      "address": "Washington Street and Essex st",
      "city": "Boston",
      "state": "MA",
      "country_code": "US",
      "hotel_rating": 4,
      "phone_number": null,
      "website": null,
      "pricePerNight": 303,
      "childrenFriendly": false,
      "petsAllowed": true,
      "image": "https://source.unsplash.com/featured/?hotel,room,4354"
    },
    {
      "id": 677565,
      "name": "Industrial 2BR in Downtown Crossing by Sonder",
      "address": "Washington Street and Essex st",
      "city": "Boston",
      "state": "MA",
      "country_code": "US",
      "hotel_rating": 4,
      "phone_number": null,
      "website": null,
      "pricePerNight": 204,
      "childrenFriendly": false,
      "petsAllowed": false,
      "image": "https://source.unsplash.com/featured/?hotel,room,3777"
    },
    {
      "id": 677571,
      "name": "Lovely Brighton Suites by Sonder",
      "address": "Commonwealth Avenue",
      "city": "Boston",
      "state": "MA",
      "country_code": "US",
      "hotel_rating": 3.5,
      "phone_number": null,
      "website": null,
      "pricePerNight": 398,
      "childrenFriendly": false,
      "petsAllowed": false,
      "image": "https://source.unsplash.com/featured/?hotel,room,1254"
    },
    {
      "id": 724715,
      "name": "Modern 2BR in Downtown Crossing by Sonder",
      "address": "Hamilton Place",
      "city": "Boston",
      "state": "MA",
      "country_code": "US",
      "hotel_rating": 4,
      "phone_number": null,
      "website": null,
      "pricePerNight": 270,
      "childrenFriendly": false,
      "petsAllowed": true,
      "image": "https://source.unsplash.com/featured/?hotel,room,9119"
    },
    {
      "id": 677574,
      "name": "Loft Style 2BR in Downtown Crossing by Sonder",
      "address": "Washington Street and Essex st",
      "city": "Boston",
      "state": "MA",
      "country_code": "US",
      "hotel_rating": 4,
      "phone_number": null,
      "website": null,
      "pricePerNight": 296,
      "childrenFriendly": false,
      "petsAllowed": true,
      "image": "https://source.unsplash.com/featured/?hotel,room,9129"
    },
    {
      "id": 677577,
      "name": "Chic 3BR in Lower Roxbury by Sonder",
      "address": "Tremont Street and St Cyprians Pl",
      "city": "Boston",
      "state": "MA",
      "country_code": "US",
      "hotel_rating": 3.5,
      "phone_number": null,
      "website": null,
      "pricePerNight": 301,
      "childrenFriendly": false,
      "petsAllowed": true,
      "image": "https://source.unsplash.com/featured/?hotel,room,6875"
    },
    {
      "id": 757401,
      "name": "Stunning 1BR in Theater District by Sonder",
      "address": "Warrenton Street",
      "city": "Boston",
      "state": "MA",
      "country_code": "US",
      "hotel_rating": 3.5,
      "phone_number": null,
      "website": null,
      "pricePerNight": 84,
      "childrenFriendly": false,
      "petsAllowed": true,
      "image": "https://source.unsplash.com/featured/?hotel,room,4585"
    }
  ]
}